shtrie/__init__.py
shtrie-0.1.0.dist-info/LICENSE
shtrie-0.1.0.dist-info/METADATA
shtrie-0.1.0.dist-info/WHEEL
shtrie-0.1.0.dist-info/top_level.txt
shtrie-0.1.0.dist-info/RECORD
