Metadata-Version: 2.1
Name: shtrie
Version: 0.1.0
Summary: Single-hash-table Trie
Author-email: Vee Satayamas <vsatayamas@gmail.com>
Project-URL: homepage, https://git.sr.ht/~veer66/shtrie
Keywords: trie
Classifier: Programming Language :: Python :: 3
Classifier: License :: OSI Approved :: Apache Software License
Classifier: Intended Audience :: Developers
Classifier: Operating System :: OS Independent
Classifier: Topic :: Software Development :: Libraries
License-File: LICENSE
